lib_clickbot/__init__.py
lib_clickbot/__main__.py
lib_clickbot/clickbot.py
lib_clickbot/events.py
lib_clickbot/logger.py
lib_clickbot-0.1.1.dist-info/AUTHORS
lib_clickbot-0.1.1.dist-info/METADATA
lib_clickbot-0.1.1.dist-info/WHEEL
lib_clickbot-0.1.1.dist-info/entry_points.txt
lib_clickbot-0.1.1.dist-info/top_level.txt
lib_clickbot-0.1.1.dist-info/RECORD
